{
  "lessonId": "L41",
  "classId": "nail-care-techniques",
  "title": "Why Aftercare Matters",
  "titleVi": "Tại Sao Việc Chăm Sóc Móng Quan Trọng",
  "level": "B1",
  "context": "Dùng những câu này để giải thích cho khách hiểu tại sao việc chăm sóc móng sau khi làm lại quan trọng.",
  "phrases": [
    { "english": "Aftercare keeps your nails looking nice.", "vietnamese": "Chăm sóc sau khi làm giúp móng đẹp lâu hơn.", "pronunciation": "af-ter-ker kips yor nailz lu-king nais" },
    { "english": "Don't put lotion on your nails.", "vietnamese": "Đừng bôi kem dưỡng lên móng.", "pronunciation": "dont put lo-shən on yor nailz" },
    { "english": "Come back in two weeks for a fill.", "vietnamese": "Hai tuần nữa quay lại dặm móng nhé.", "pronunciation": "kum bak in tu wiks for uh fil" }
  ]
}
